[
  {
    "results": [
      {
        "final": true,
        "alternatives": [
          {
            "transcript": "on June twenty first nineteen seventy eight twenty two year old karla brown was found brutally murdered in the basement of a home ",
            "confidence": 0.97
          }
        ]
      },
      {
        "final": true,
        "alternatives": [
          {
            "transcript": "it looked as if the killer had committed the perfect crime ",
            "confidence": 0.98
          }
        ]
      },
      {
        "final": true,
        "alternatives": [
          {
            "transcript": "police could find very little evidence ",
            "confidence": 0.94
          }
        ]
      },
      {
        "final": true,
        "alternatives": [
          {
            "transcript": "but years later investigators noticed something on a crime scene photographs that had previously been overlooked ",
            "confidence": 0.92
          }
        ]
      },
      {
        "final": true,
        "alternatives": [
          {
            "transcript": "the killer had left behind ",
            "confidence": 0.97
          }
        ]
      },
      {
        "final": true,
        "alternatives": [
          {
            "transcript": "this ",
            "confidence": 0.14
          }
        ]
      },
      {
        "final": true,
        "alternatives": [
          {
            "transcript": "twenty two year old karla brown and her fiance a man we'll call Marquardt had recently purchased a home together in wood river Illinois ",
            "confidence": 0.8
          }
        ]
      },
      {
        "final": true,
        "alternatives": [
          {
            "transcript": "although the couple had a rocky past friends and family saw this as the beginning of a new phase in their relationship ",
            "confidence": 0.95
          }
        ]
      },
      {
        "final": true,
        "alternatives": [
          {
            "transcript": "Carl brown was so beautiful girl ",
            "confidence": 0.79
          }
        ]
      },
      {
        "final": true,
        "alternatives": [
          {
            "transcript": "for young woman was very popular in your hometown ",
            "confidence": 0.79
          }
        ]
      },
      {
        "final": true,
        "alternatives": [
          {
            "transcript": "yeah I had taken some college classes had been a high school cheerleader was one of those girls that everybody knew girls like guys like %HESITATION she's just one of those people that was special and everybody recognize that on June twenty first Carla brown took the day off from work to unpack ",
            "confidence": 0.88
          }
        ]
      },
      {
        "final": true,
        "alternatives": [
          {
            "transcript": "yeah ",
            "confidence": 0.39
          }
        ]
      },
      {
        "final": true,
        "alternatives": [
          {
            "transcript": "right and spoke to one of her friends on the telephone maybe we can have you over for dinner they had talked for a few minutes to talk about getting together later on that afternoon what is a good match herbs ",
            "confidence": 0.81
          }
        ]
      },
      {
        "final": true,
        "alternatives": [
          {
            "transcript": "and Carlos right to the conversation and said listen I'll have to call you back I'll see you later somebody at the door and that was the last %HESITATION their friend never talked to ",
            "confidence": 0.79
          }
        ]
      },
      {
        "final": true,
        "alternatives": [
          {
            "transcript": "around five thirty that afternoon Carless fiance and his friends stop by the house after work ",
            "confidence": 0.86
          }
        ]
      },
      {
        "final": true,
        "alternatives": [
          {
            "transcript": "when they walk into the basement they saw a horrible sight ",
            "confidence": 0.88
          }
        ]
      },
      {
        "final": true,
        "alternatives": [
          {
            "transcript": "Carlos lying face down in a bucket of water ",
            "confidence": 0.82
          }
        ]
      },
      {
        "final": true,
        "alternatives": [
          {
            "transcript": "she had her hands tied behind her there was evidence of struggle a death struggle in the basement %HESITATION and and the suit is very strong suggestion of a sexual rape ",
            "confidence": 0.88
          }
        ]
      },
      {
        "final": true,
        "alternatives": [
          {
            "transcript": "but investigators were confused about some of the things they saw ",
            "confidence": 0.98
          }
        ]
      },
      {
        "final": true,
        "alternatives": [
          {
            "transcript": "there were two men socks tied around Carlos neck they were tied neatly inconsistent with what you would expect to see in a life and death struggle ",
            "confidence": 0.83
          }
        ]
      },
      {
        "final": true,
        "alternatives": [
          {
            "transcript": "the white electrical cord used to tied the victim's hands was not tight enough to effectively restrain an individual during an assault there was too much length of cord behind her to wear her hands could come up in front of her it would seem like to me that she would have access to the attacker given that much freedom ",
            "confidence": 0.9
          }
        ]
      },
      {
        "final": true,
        "alternatives": [
          {
            "transcript": "was a length of rope that was tied between the two wrist ",
            "confidence": 0.89
          }
        ]
      },
      {
        "final": true,
        "alternatives": [
          {
            "transcript": "she was found wearing a sweater %HESITATION fiancee said she would never wear in the summer ",
            "confidence": 0.95
          }
        ]
      },
      {
        "final": true,
        "alternatives": [
          {
            "transcript": "the top button was fastened another inconsistency with a life and death struggle ",
            "confidence": 0.82
          }
        ]
      },
      {
        "final": true,
        "alternatives": [
          {
            "transcript": "the socks around Carless network from inside the home ",
            "confidence": 0.62
          }
        ]
      },
      {
        "final": true,
        "alternatives": [
          {
            "transcript": "the make to one was found in her fiance's dresser the other was under the sofa in the adjacent room under the sofa was a puddle of water tainted with blood the sofa cushions were also wet blood drops on the floor near the so ",
            "confidence": 0.79
          }
        ]
      },
      {
        "final": true,
        "alternatives": [
          {
            "transcript": "in the rafters was a coffee carafe from the kitchen to homicide investigators it looked as if the coffee carafe had been used to rinse blood from the sofa cushions ",
            "confidence": 0.86
          }
        ]
      },
      {
        "final": true,
        "alternatives": [
          {
            "transcript": "the attack occurred near the sofa and the body was later moved into an adjacent room and placed into the barrel of water ",
            "confidence": 0.95
          }
        ]
      },
      {
        "final": true,
        "alternatives": [
          {
            "transcript": "the crime scene staging told investigators that the perpetrator spent a great deal of time inside the house after the murders but who knew that Carla brown was home and the loan on the date of the merger and who would have felt free to spend so much time in the home cleaning up and staging the C. ",
            "confidence": 0.85
          }
        ]
      },
      {
        "final": true,
        "alternatives": [
          {
            "transcript": "police began their investigation with a close look at Carla brown's fiancee ",
            "confidence": 0.86
          }
        ]
      },
      {
        "final": true,
        "alternatives": [
          {
            "transcript": "the autopsy report on Carla brown indicated death by strangulation although she was found nude from the waist down there were no signs of sexual assault ",
            "confidence": 0.94
          }
        ]
      },
      {
        "final": true,
        "alternatives": [
          {
            "transcript": "investigators were convinced that the killer spent a great deal of time in the house after the merger staging the crime scene ",
            "confidence": 0.91
          }
        ]
      },
      {
        "final": true,
        "alternatives": [
          {
            "transcript": "I didn't know mark very well although they had dated for a number of years off and on and there were times in their relationship that ",
            "confidence": 0.9
          }
        ]
      },
      {
        "final": true,
        "alternatives": [
          {
            "transcript": "it wasn't great but I she seems to always be ",
            "confidence": 0.82
          }
        ]
      },
      {
        "final": true,
        "alternatives": [
          {
            "transcript": "AZ about him anyway police also questioned to neighbors who had been sitting in the yard next door on the day Carla and her fiance removing it ",
            "confidence": 0.84
          }
        ]
      },
      {
        "final": true,
        "alternatives": [
          {
            "transcript": "I called ",
            "confidence": 0.28
          }
        ]
      },
      {
        "final": true,
        "alternatives": [
          {
            "transcript": "Colorado ",
            "confidence": 0.18
          }
        ]
      },
      {
        "final": true,
        "alternatives": [
          {
            "transcript": "I'm John Francie we went to school together remember me ",
            "confidence": 0.81
          }
        ]
      },
      {
        "final": true,
        "alternatives": [
          {
            "transcript": "both men had alibis as to where they were on the day of the murder and they both willingly took lie detector test and passed ",
            "confidence": 0.9
          }
        ]
      },
      {
        "final": true,
        "alternatives": [
          {
            "transcript": "with no other leads police asked the FBI for a psychological profile of the killer and turned to FBI behavioral analyst John Douglas in my restriction began to break down crimes by disorganized and organized disorganized means extra extremely %HESITATION sloppy carelessness on the part of the offender %HESITATION the crime could be very very %HESITATION impulsive organize means that there's a high degree high level of criminal sophistication on the part of the subject to Douglas this crime scene was disorganized an indication that the killer was inexperienced and probably had never killed before he came to the home with no intention of committing murder but did so after some sort of confrontation or rejection ",
            "confidence": 0.88
          }
        ]
      },
      {
        "final": true,
        "alternatives": [
          {
            "transcript": "since we spend so much time inside the home Douglas believed that he was familiar with the dementor routine and might be living in the neighborhood or very close by ",
            "confidence": 0.86
          }
        ]
      },
      {
        "final": true,
        "alternatives": [
          {
            "transcript": "Douglas said the killer was a non married white male in his mid to late twenties high school educated with a sloppy appearance ",
            "confidence": 0.91
          }
        ]
      },
      {
        "final": true,
        "alternatives": [
          {
            "transcript": "the use of electrical cord to tied the victim's hands indicated the killer had taken shop classes or have vocational training ",
            "confidence": 0.88
          }
        ]
      },
      {
        "final": true,
        "alternatives": [
          {
            "transcript": "luckless also told investigators that they may have already interviewed the murderer and that he was capable of passing a polygraph test and then it got kind of spooky I mean I was sitting there and I wasn't sure I was believing what he was saying after a certain point he started talking about ",
            "confidence": 0.9
          }
        ]
      },
      {
        "final": true,
        "alternatives": [
          {
            "transcript": "how this individual would react ",
            "confidence": 0.97
          }
        ]
      },
      {
        "final": true,
        "alternatives": [
          {
            "transcript": "and what kind of vehicle he'd be driving ",
            "confidence": 0.97
          }
        ]
      },
      {
        "final": true,
        "alternatives": [
          {
            "transcript": "and ",
            "confidence": 0.85
          }
        ]
      },
      {
        "final": true,
        "alternatives": [
          {
            "transcript": "he started talking about a volts wagon there is high probability this guy I'd be able to drive a Volkswagen ",
            "confidence": 0.73
          }
        ]
      },
      {
        "final": true,
        "alternatives": [
          {
            "transcript": "and that it would be red or orange in color this led investigators to focus once again on the two men sitting next door on the day Carla brown and her fiance removing ",
            "confidence": 0.9
          }
        ]
      },
      {
        "final": true,
        "alternatives": [
          {
            "transcript": "but investigators needed more than just a psychological profile they needed hard ",
            "confidence": 0.87
          }
        ]
      },
      {
        "final": true,
        "alternatives": [
          {
            "transcript": "I am seen technician how the bush remained ",
            "confidence": 0.65
          }
        ]
      },
      {
        "final": true,
        "alternatives": [
          {
            "transcript": "by the call of brown ",
            "confidence": 0.68
          }
        ]
      },
      {
        "final": true,
        "alternatives": [
          {
            "transcript": "for one thing he and his colleagues could not determine what caused the ",
            "confidence": 0.89
          }
        ]
      },
      {
        "final": true,
        "alternatives": [
          {
            "transcript": "all the problems the second chance ",
            "confidence": 0.45
          }
        ]
      },
      {
        "final": true,
        "alternatives": [
          {
            "transcript": "the first real break in the case occurred when bush attended a seminar on image enhancement at the university of New Mexico Dr Homer Campbell taught that seminar he worked for the state of New Mexico as a medical investigation ",
            "confidence": 0.89
          }
        ]
      },
      {
        "final": true,
        "alternatives": [
          {
            "transcript": "Dr Campbell was demonstrating a photographic technique that uses cameras monitors and computers to show details of crime scene photographs that cannot otherwise be see this is a technique that has been used for several years both by engineers and nondestructive testing of materials and also by archaeologist %HESITATION looking at aerial photographs defined the ancient ruins ",
            "confidence": 0.85
          }
        ]
      },
      {
        "final": true,
        "alternatives": [
          {
            "transcript": "after the seminar bush told doctor Campbell about the Carla brown case and I said Dr do I have a case for you ",
            "confidence": 0.9
          }
        ]
      },
      {
        "final": true,
        "alternatives": [
          {
            "transcript": "and I told them about the color brown case in that ",
            "confidence": 0.74
          }
        ]
      },
      {
        "final": true,
        "alternatives": [
          {
            "transcript": "we were never able to identify what type instrument hadn't damaged her face I asked him to please send me the photographs %HESITATION ",
            "confidence": 0.8
          }
        ]
      },
      {
        "final": true,
        "alternatives": [
          {
            "transcript": "the head of ",
            "confidence": 0.53
          }
        ]
      },
      {
        "final": true,
        "alternatives": [
          {
            "transcript": "deceased person and also to send me an autopsy report ",
            "confidence": 0.52
          }
        ]
      },
      {
        "final": true,
        "alternatives": [
          {
            "transcript": "Dr Campbell used his image enhancement equipment to look more closely at the crime scene photos of Carla brown the system not only improves the contrast of the photographs the can also create what appeared to be three dimensional view adding depth to the image when Dr Campbell was through ",
            "confidence": 0.85
          }
        ]
      },
      {
        "final": true,
        "alternatives": [
          {
            "transcript": "he knew what caused the injuries to Carla brown space it tells me that maybe the TV tray may have been the instrument that she was hit in the head with this TV tray was lying on the floor within three Florida the ",
            "confidence": 0.66
          }
        ]
      },
      {
        "final": true,
        "alternatives": [
          {
            "transcript": "victim where she had probably been on the couch but I missed it ",
            "confidence": 0.8
          }
        ]
      },
      {
        "final": true,
        "alternatives": [
          {
            "transcript": "the tray tables were still in storage untouched in the two years since the merger ",
            "confidence": 0.81
          }
        ]
      },
      {
        "final": true,
        "alternatives": [
          {
            "transcript": "in an extraordinary piece of luck Dr Campbell found microscopic traces of blood and hair still present on the tray table ",
            "confidence": 0.91
          }
        ]
      },
      {
        "final": true,
        "alternatives": [
          {
            "transcript": "and what Dr Campbell said next with even more with the ",
            "confidence": 0.86
          }
        ]
      },
      {
        "final": true,
        "alternatives": [
          {
            "transcript": "this is what about the bite mark ",
            "confidence": 0.79
          }
        ]
      },
      {
        "final": true,
        "alternatives": [
          {
            "transcript": "and a half by Marc Webb by mark what are you talking about ",
            "confidence": 0.74
          }
        ]
      },
      {
        "final": true,
        "alternatives": [
          {
            "transcript": "when we looked at photographs and went ahead and enhanced and magnified ",
            "confidence": 0.64
          }
        ]
      },
      {
        "final": true,
        "alternatives": [
          {
            "transcript": "present on the shoulder was a bite injury on the show and by looking at that by the injury you could actually pick out individual T. all the way across ",
            "confidence": 0.8
          }
        ]
      },
      {
        "final": true,
        "alternatives": [
          {
            "transcript": "yeah I tried that for five I would ",
            "confidence": 0.72
          }
        ]
      },
      {
        "final": true,
        "alternatives": [
          {
            "transcript": "as I witness is going to make mistakes things like fingerprints down ",
            "confidence": 0.75
          }
        ]
      },
      {
        "final": true,
        "alternatives": [
          {
            "transcript": "and it was my understanding that bite marks properly preserved %HESITATION with an identified defendant could give you the defendant as good as a fingerprint ",
            "confidence": 0.86
          }
        ]
      },
      {
        "final": true,
        "alternatives": [
          {
            "transcript": "the killer had left behind a slew ",
            "confidence": 0.76
          }
        ]
      },
      {
        "final": true,
        "alternatives": [
          {
            "transcript": "all investigators needed now was a suspect ",
            "confidence": 0.9
          }
        ]
      },
      {
        "final": true,
        "alternatives": [
          {
            "transcript": "two years after the brutal murder of a twenty two year old karla brown investigators got the break they needed one of photographic enhancement revealed a bite mark on Carly shoulder police now turned to the two men sitting in the yard next door when Carla brown moved into our new home ",
            "confidence": 0.9
          }
        ]
      },
      {
        "final": true,
        "alternatives": [
          {
            "transcript": "both match the F. B. I.'s behavioral profile of the killer police check their alibis again although both had passed a polygraph test police discovered that John Plantae had spoken about the merger to others Jop Randy had mentioned to his friends that he had seen her body that day that he looked over the shoulder of some policemen while they were investigating in the basement and he described %HESITATION the condition of her body and he even mentioned that she had bite marks on her neck and collarbone ",
            "confidence": 0.89
          }
        ]
      },
      {
        "final": true,
        "alternatives": [
          {
            "transcript": "the police were the only ones inside the house after Carla brown's body was found ",
            "confidence": 0.82
          }
        ]
      },
      {
        "final": true,
        "alternatives": [
          {
            "transcript": "shock to us as police officers because there's no way that he can and known that unless you put the bite marks there ",
            "confidence": 0.78
          }
        ]
      },
      {
        "final": true,
        "alternatives": [
          {
            "transcript": "also the information about the location of the body the way the body was found the only way that that would have been known it is either to have been there on the investigation ",
            "confidence": 0.95
          }
        ]
      },
      {
        "final": true,
        "alternatives": [
          {
            "transcript": "%HESITATION or to put the body there yourself because we never released that information to the public or to the media ",
            "confidence": 0.9
          }
        ]
      },
      {
        "final": true,
        "alternatives": [
          {
            "transcript": "since the bite marks were overlooked during the original autopsy investigators wanted to make sure nothing else was missed so Carla brown's body was exhumed for a second autopsy ",
            "confidence": 0.92
          }
        ]
      },
      {
        "final": true,
        "alternatives": [
          {
            "transcript": "this time it was performed by Dr Mary case the chief medical examiner for St Louis county in the original autopsy %HESITATION there was no ligature strangulation and the body was examined and for some reason they had was not examined and so I opened the cranial cavity and there was bruising in the scalp somebody struck her on the head and question is whether or not for example this alone would cause loss of consciousness ",
            "confidence": 0.89
          }
        ]
      },
      {
        "final": true,
        "alternatives": [
          {
            "transcript": "Dr case thought that Carla brown may have been alive when she was placed in the barrel of water because when she was found it was phone around her mouth because she was in the water in she was producing that phone ",
            "confidence": 0.9
          }
        ]
      },
      {
        "final": true,
        "alternatives": [
          {
            "transcript": "I feel like there may be some component grounding that she was still on even though she'd been strangled she was still maybe to a minimal degree of breathing because I I believe that she may have breathed in some water ",
            "confidence": 0.82
          }
        ]
      },
      {
        "final": true,
        "alternatives": [
          {
            "transcript": "during the autopsy more photographs were taken of the suspected bite wounds which were sent to the New York state police forensic unit for an independent evaluation ",
            "confidence": 0.93
          }
        ]
      },
      {
        "final": true,
        "alternatives": [
          {
            "transcript": "S. accusers wanted to make sure that the mark on Carla brown's neck was in fact a bike ",
            "confidence": 0.69
          }
        ]
      },
      {
        "final": true,
        "alternatives": [
          {
            "transcript": "patterning jury on call brown's neck and all the characteristics that a bite mark would have ",
            "confidence": 0.67
          }
        ]
      },
      {
        "final": true,
        "alternatives": [
          {
            "transcript": "Dr Levine was asked to compare the bite wound to three different dental casts prosecutors sent along for analysis Dr Levine no idea to whom the cast along ",
            "confidence": 0.84
          }
        ]
      },
      {
        "final": true,
        "alternatives": [
          {
            "transcript": "after making wax impressions of the models Dr Levin concluded two of the models were not consistent with the bite wound I took the third model ",
            "confidence": 0.88
          }
        ]
      },
      {
        "final": true,
        "alternatives": [
          {
            "transcript": "and examine the only %HESITATION individual characteristics that those teeth would have cost compared those characteristics with the characteristics on the clarified photograph of Carla brown's neck %HESITATION that I had and came to the opinion that only that model was consistent with having caused of that pattern injury %HESITATION that bite mark he measured the teeth he went back to the photograph he turned in different ways he held them up in the air finally he laid the downward pressures on the table and he pointed to a man he said that year my ",
            "confidence": 0.81
          }
        ]
      },
      {
        "final": true,
        "alternatives": [
          {
            "transcript": "model number three ",
            "confidence": 0.85
          }
        ]
      },
      {
        "final": true,
        "alternatives": [
          {
            "transcript": "belonged to John Prine T. ",
            "confidence": 0.76
          }
        ]
      },
      {
        "final": true,
        "alternatives": [
          {
            "transcript": "interesting ",
            "confidence": 0.62
          }
        ]
      },
      {
        "final": true,
        "alternatives": [
          {
            "transcript": "Randy also matched John Douglas's psychological profile he was in his late twenties had a history of troubled relationships with women he attended industrial arts school and had a sloppy on camp appearance ",
            "confidence": 0.87
          }
        ]
      },
      {
        "final": true,
        "alternatives": [
          {
            "transcript": "a great deal of time in the neighborhood often visiting his friend lives next door to Carla brown ",
            "confidence": 0.87
          }
        ]
      },
      {
        "final": true,
        "alternatives": [
          {
            "transcript": "and just as John Douglas had predicted ",
            "confidence": 0.78
          }
        ]
      },
      {
        "final": true,
        "alternatives": [
          {
            "transcript": "he had passed an earlier polygraph test the most unusual aspect of Douglass's profile was the prediction that he would be driving a red Volkswagen ",
            "confidence": 0.81
          }
        ]
      },
      {
        "final": true,
        "alternatives": [
          {
            "transcript": "%HESITATION where that came from the only job I could say but in fact it turned out that the individual did have Volkswagen ",
            "confidence": 0.85
          }
        ]
      },
      {
        "final": true,
        "alternatives": [
          {
            "transcript": "prosecutors believe that when Carla brown's fiancee left for work John ",
            "confidence": 0.92
          }
        ]
      },
      {
        "final": true,
        "alternatives": [
          {
            "transcript": "the over and knocked on the door maybe we can have you ever for dinner Carlo was talking on the telephone ",
            "confidence": 0.85
          }
        ]
      },
      {
        "final": true,
        "alternatives": [
          {
            "transcript": "when I call you back ",
            "confidence": 0.74
          }
        ]
      },
      {
        "final": true,
        "alternatives": [
          {
            "transcript": "what do you want ",
            "confidence": 0.86
          }
        ]
      },
      {
        "final": true,
        "alternatives": [
          {
            "transcript": "when we talk ",
            "confidence": 0.36
          }
        ]
      },
      {
        "final": true,
        "alternatives": [
          {
            "transcript": "in some kind of argument or struggle possibly after she had rejected twenty sexual advances ",
            "confidence": 0.81
          }
        ]
      },
      {
        "final": true,
        "alternatives": [
          {
            "transcript": "more stir into the basement with the tray tables ",
            "confidence": 0.75
          }
        ]
      },
      {
        "final": true,
        "alternatives": [
          {
            "transcript": "some point ",
            "confidence": 0.65
          }
        ]
      },
      {
        "final": true,
        "alternatives": [
          {
            "transcript": "%HESITATION on the shoulder ",
            "confidence": 0.86
          }
        ]
      },
      {
        "final": true,
        "alternatives": [
          {
            "transcript": "her ",
            "confidence": 0.29
          }
        ]
      },
      {
        "final": true,
        "alternatives": [
          {
            "transcript": "he staged the scene to make it appear to be a sexual assault ",
            "confidence": 0.86
          }
        ]
      },
      {
        "final": true,
        "alternatives": [
          {
            "transcript": "changed for clones he made the mistake ",
            "confidence": 0.78
          }
        ]
      },
      {
        "final": true,
        "alternatives": [
          {
            "transcript": "the top of the first to see stay ",
            "confidence": 0.68
          }
        ]
      },
      {
        "final": true,
        "alternatives": [
          {
            "transcript": "he tied her hands with electrical ",
            "confidence": 0.99
          }
        ]
      },
      {
        "final": true,
        "alternatives": [
          {
            "transcript": "the socks around her neck ",
            "confidence": 0.92
          }
        ]
      },
      {
        "final": true,
        "alternatives": [
          {
            "transcript": "please turn into the water while she was unconscious but still alive ",
            "confidence": 0.87
          }
        ]
      },
      {
        "final": true,
        "alternatives": [
          {
            "transcript": "right to remove the blood stains on the sofa with water carried from the kitchen and the coffee carafe which she left in the rafters above the sub ",
            "confidence": 0.72
          }
        ]
      },
      {
        "final": true,
        "alternatives": [
          {
            "transcript": "hello caller was wearing that day were never found ",
            "confidence": 0.64
          }
        ]
      },
      {
        "final": true,
        "alternatives": [
          {
            "transcript": "trending they had taken them as a truck ",
            "confidence": 0.58
          }
        ]
      },
      {
        "final": true,
        "alternatives": [
          {
            "transcript": "in July of nineteen eighty three John twenty was tried and convicted of first degree murder and was sentenced to seventy five years in the state penitentiary ",
            "confidence": 0.95
          }
        ]
      },
      {
        "final": true,
        "alternatives": [
          {
            "transcript": "after five long years Carla brown's family finally has some closure I would like to tell him that he he took away a very wonderful person %HESITATION who had a lot to offer an up in a family who cared very much about Carla ",
            "confidence": 0.93
          }
        ]
      },
      {
        "final": true,
        "alternatives": [
          {
            "transcript": "and that it was very ",
            "confidence": 0.97
          }
        ]
      },
      {
        "final": true,
        "alternatives": [
          {
            "transcript": "very selfish of him to ",
            "confidence": 0.98
          }
        ]
      },
      {
        "final": true,
        "alternatives": [
          {
            "transcript": "to not consider another person's life ",
            "confidence": 0.91
          }
        ]
      },
      {
        "final": true,
        "alternatives": [
          {
            "transcript": "ana S. as something as something that can just be thrown away ",
            "confidence": 0.74
          }
        ]
      },
      {
        "final": true,
        "alternatives": [
          {
            "transcript": "I ",
            "confidence": 0.16
          }
        ]
      },
      {
        "final": true,
        "alternatives": [
          {
            "transcript": "on a on a particular day ",
            "confidence": 0.93
          }
        ]
      },
      {
        "final": true,
        "alternatives": [
          {
            "transcript": "he got caught because the techniques of investigation and law enforcement completely overpowered him ",
            "confidence": 0.89
          }
        ]
      },
      {
        "final": true,
        "alternatives": [
          {
            "transcript": "he got away with the crime because he was lucky he got caught because law enforcement change this log ",
            "confidence": 0.86
          }
        ]
      },
      {
        "final": true,
        "alternatives": [
          {
            "transcript": "don Weber along with journalist Charles Bosworth chronicled the many ups and downs of this case and a best selling book silent with ",
            "confidence": 0.83
          }
        ]
      },
      {
        "final": true,
        "alternatives": [
          {
            "transcript": "Carl's family was so intrigued by the bite mark evidence that %HESITATION she embroidered wool tapestry that she presented to dom Weber as a token of appreciation and it offers the slogan that don had used you can lie through your teeth that your teams don't lie and around the border is the %HESITATION pattern of rectangles space rectangle space triangle which is the bite mark pattern that dont have proved had been made by John printing ",
            "confidence": 0.8
          }
        ]
      }
    ],
    "result_index": 0
  }
]