[
  {
    "results": [
      {
        "final": true,
        "alternatives": [
          {
            "transcript": "while on a business trip in nineteen eighty six ",
            "confidence": 0.97
          }
        ]
      },
      {
        "final": true,
        "alternatives": [
          {
            "transcript": "spent the morning jogging near his hotel in downtown Saint Louis ",
            "confidence": 0.95
          }
        ]
      },
      {
        "final": true,
        "alternatives": [
          {
            "transcript": "when he returned to his hotel room ",
            "confidence": 0.98
          }
        ]
      },
      {
        "final": true,
        "alternatives": [
          {
            "transcript": "discover the path ",
            "confidence": 0.47
          }
        ]
      },
      {
        "final": true,
        "alternatives": [
          {
            "transcript": "the medical examiner ruled the death was by drowning ",
            "confidence": 0.78
          }
        ]
      },
      {
        "final": true,
        "alternatives": [
          {
            "transcript": "similarly accidentals but homicide investigators weren't so sure ",
            "confidence": 0.72
          }
        ]
      },
      {
        "final": true,
        "alternatives": [
          {
            "transcript": "this ",
            "confidence": 0.26
          }
        ]
      },
      {
        "final": true,
        "alternatives": [
          {
            "transcript": "post met Julie big band when they were both students at the university of southern Mississippi in the nineteen sixties ",
            "confidence": 0.87
          }
        ]
      },
      {
        "final": true,
        "alternatives": [
          {
            "transcript": "they married in nineteen sixty seven had two daughters ",
            "confidence": 1
          }
        ]
      },
      {
        "final": true,
        "alternatives": [
          {
            "transcript": "and moved to New World ",
            "confidence": 0.45
          }
        ]
      },
      {
        "final": true,
        "alternatives": [
          {
            "transcript": "I went to work in the real estate business ",
            "confidence": 0.97
          }
        ]
      },
      {
        "final": true,
        "alternatives": [
          {
            "transcript": "his outgoing personality and sophisticated manner made him a successful salesman right from the start I thought that was a good fellow what you'd expect a real estate salesman to be kind of relentlessly cheerful after a few years at post became part owner of the Wagner Truax real estate firm ",
            "confidence": 0.88
          }
        ]
      },
      {
        "final": true,
        "alternatives": [
          {
            "transcript": "Julie post also joined the company and was very successful selling over a million dollars of real estate every year from nineteen eighty two on ",
            "confidence": 0.93
          }
        ]
      },
      {
        "final": true,
        "alternatives": [
          {
            "transcript": "in June of nineteen eighty six the post's attended a realistic convention in Saint Louis Missouri at the omni hotel at Union Station ",
            "confidence": 0.95
          }
        ]
      },
      {
        "final": true,
        "alternatives": [
          {
            "transcript": "on the morning of June third at post decided to go jogging before the meeting started he said he drew his wife of bath and will Kerr before leaving around seven AM ",
            "confidence": 0.87
          }
        ]
      },
      {
        "final": true,
        "alternatives": [
          {
            "transcript": "finally ",
            "confidence": 0.95
          }
        ]
      },
      {
        "final": true,
        "alternatives": [
          {
            "transcript": "on his way out he thanked the hotel's concierge for a suggestion she made to the post the day before really wonderful so glad the wonderful place this anything else I can do for you just let me know ",
            "confidence": 0.84
          }
        ]
      },
      {
        "final": true,
        "alternatives": [
          {
            "transcript": "Sir have a nice day yes I am thank you and I try and post jog past Busch Stadium ",
            "confidence": 0.6
          }
        ]
      },
      {
        "final": true,
        "alternatives": [
          {
            "transcript": "around the city's famous arch and return to the hotel at seven forty ",
            "confidence": 0.86
          }
        ]
      },
      {
        "final": true,
        "alternatives": [
          {
            "transcript": "%HESITATION ",
            "confidence": 0.3
          }
        ]
      },
      {
        "final": true,
        "alternatives": [
          {
            "transcript": "great ",
            "confidence": 0.26
          }
        ]
      },
      {
        "final": true,
        "alternatives": [
          {
            "transcript": "and we're working on this morning ",
            "confidence": 0.55
          }
        ]
      },
      {
        "final": true,
        "alternatives": [
          {
            "transcript": "when he entered his hotel room he said he discovered his wife lying face down and unconscious in the back ",
            "confidence": 0.88
          }
        ]
      },
      {
        "final": true,
        "alternatives": [
          {
            "transcript": "after pulling her body from the water he call for an ambulance at seven forty three percent of families place ",
            "confidence": 0.81
          }
        ]
      },
      {
        "final": true,
        "alternatives": [
          {
            "transcript": "it looked as if Julie post lost her footing and grab the towel ring which pulled out of the wall ",
            "confidence": 0.79
          }
        ]
      },
      {
        "final": true,
        "alternatives": [
          {
            "transcript": "at the hospital Julie post was pronounced dead she was thirty nine years old ",
            "confidence": 0.9
          }
        ]
      },
      {
        "final": true,
        "alternatives": [
          {
            "transcript": "the autopsy revealed that death was due to drowning ",
            "confidence": 0.93
          }
        ]
      },
      {
        "final": true,
        "alternatives": [
          {
            "transcript": "ed post immediately phoned his brother who was a lawyer together they photographed the broken tiles rang in mount for a lawsuit against a hotel his brother told police when there's a Lowe's almost sold for four hundred fifty million dollars you watch ",
            "confidence": 0.72
          }
        ]
      },
      {
        "final": true,
        "alternatives": [
          {
            "transcript": "and post was convinced that had it not been for the faulty powering his wife Julie might still be alive ",
            "confidence": 0.8
          }
        ]
      },
      {
        "final": true,
        "alternatives": [
          {
            "transcript": "after Julie post was pronounced dead an autopsy was performed in St Louis before the body was transported to New Orleans for Barry ",
            "confidence": 0.89
          }
        ]
      },
      {
        "final": true,
        "alternatives": [
          {
            "transcript": "the autopsy found no sign of alcohol or drugs in her system ",
            "confidence": 0.92
          }
        ]
      },
      {
        "final": true,
        "alternatives": [
          {
            "transcript": "there were no skull fractures or bleeding in the brain that would have been present at the victim had been struck in the head before drowning in short the path colleges could find no evidence of foul play I was certainly not convinced that it was an accident ",
            "confidence": 0.9
          }
        ]
      },
      {
        "final": true,
        "alternatives": [
          {
            "transcript": "on the other hand I couldn't prove that it was anything else ",
            "confidence": 0.96
          }
        ]
      },
      {
        "final": true,
        "alternatives": [
          {
            "transcript": "on the death certificate the manner of death was undetermined ",
            "confidence": 0.96
          }
        ]
      },
      {
        "final": true,
        "alternatives": [
          {
            "transcript": "when the St Louis post dispatch reported the news of Julie posted that there were some interesting reactions ",
            "confidence": 0.84
          }
        ]
      },
      {
        "final": true,
        "alternatives": [
          {
            "transcript": "D. Joyce Hayes was a prosecutor in the district attorney's office her husband Gary was a detective in the St Louis police department ",
            "confidence": 0.85
          }
        ]
      },
      {
        "final": true,
        "alternatives": [
          {
            "transcript": "D. had just read an article about a woman who was who had drowned in the bathtub at the omni hotel and %HESITATION she said Gerry make sure you read this it doesn't sound right to me we both read the article and look at each other and said Nash ",
            "confidence": 0.85
          }
        ]
      },
      {
        "final": true,
        "alternatives": [
          {
            "transcript": "No Way ",
            "confidence": 0.98
          }
        ]
      },
      {
        "final": true,
        "alternatives": [
          {
            "transcript": "the hotel management found it hard to believe that a one hundred twenty pound woman like Julie post could have pulled the towel ring from the war since the ring had been designed to withstand more than twice that weight we went to the two adjoining rooms ",
            "confidence": 0.86
          }
        ]
      },
      {
        "final": true,
        "alternatives": [
          {
            "transcript": "I probably weighed close to two hundred twenty pounds at the time ",
            "confidence": 0.91
          }
        ]
      },
      {
        "final": true,
        "alternatives": [
          {
            "transcript": "with all my weight Honda both tolerance and both rooms and neither one of them gave nothing ",
            "confidence": 0.72
          }
        ]
      },
      {
        "final": true,
        "alternatives": [
          {
            "transcript": "post told police that he and his wife had a very good relationship but a background check of the posts finances revealed an interesting coincidence we went to the insurance company ",
            "confidence": 0.94
          }
        ]
      },
      {
        "final": true,
        "alternatives": [
          {
            "transcript": "and how long the whole ",
            "confidence": 0.71
          }
        ]
      },
      {
        "final": true,
        "alternatives": [
          {
            "transcript": "%HESITATION hello twenty seven twenty nine days %HESITATION prior to Julie post death ",
            "confidence": 0.84
          }
        ]
      },
      {
        "final": true,
        "alternatives": [
          {
            "transcript": "it had it increased your insurance like for five hundred thousand dollars now this is a woman who's making %HESITATION in the low to mid twenty thousand dollar a year range in salary and he's got this six seven hundred thousand dollar life insurance policy on his wife in a ",
            "confidence": 0.91
          }
        ]
      },
      {
        "final": true,
        "alternatives": [
          {
            "transcript": "that's when ice ",
            "confidence": 0.67
          }
        ]
      },
      {
        "final": true,
        "alternatives": [
          {
            "transcript": "begin to believe maybe we have something here police also discovered that post was enamored with a married woman who worked in his office her name was Kim %HESITATION ten ",
            "confidence": 0.92
          }
        ]
      },
      {
        "final": true,
        "alternatives": [
          {
            "transcript": "on the day of Julie posts funeral it made an unusual request came out ",
            "confidence": 0.8
          }
        ]
      },
      {
        "final": true,
        "alternatives": [
          {
            "transcript": "Kim %HESITATION ten had a twin sister and at the time of the funeral of Julie it post said the camo tan maybe when this is over you can set me up with your sister and that seemed %HESITATION a most inappropriate thing to be saying and particularly saying at the time that he's alleged to have said it ",
            "confidence": 0.84
          }
        ]
      },
      {
        "final": true,
        "alternatives": [
          {
            "transcript": "these were also suspicious about the way at post told the story of finding his wife's body the story never varied almost as if it had been rehearsed St Louis police tape recorded those conversations and %HESITATION grandma came over the edges %HESITATION ",
            "confidence": 0.83
          }
        ]
      },
      {
        "final": true,
        "alternatives": [
          {
            "transcript": "%HESITATION thing is where you are right in the water it was good at that point once I got a partially out of the top I was not prepared for what happened next which was literally fled out of that point do you think that we can get our hands on on the bottom portion again is the fact that imposed ",
            "confidence": 0.68
          }
        ]
      },
      {
        "final": true,
        "alternatives": [
          {
            "transcript": "in his ",
            "confidence": 0.56
          }
        ]
      },
      {
        "final": true,
        "alternatives": [
          {
            "transcript": "golden tongue ",
            "confidence": 0.76
          }
        ]
      },
      {
        "final": true,
        "alternatives": [
          {
            "transcript": "let me enter ",
            "confidence": 0.07
          }
        ]
      },
      {
        "final": true,
        "alternatives": [
          {
            "transcript": "Oct came off is a ",
            "confidence": 0.83
          }
        ]
      },
      {
        "final": true,
        "alternatives": [
          {
            "transcript": "is a non caring person that ",
            "confidence": 0.84
          }
        ]
      },
      {
        "final": true,
        "alternatives": [
          {
            "transcript": "had this alibi who had everything down Pat I mean he didn't change his story one iota from the first time he told to the second time he told it and some of the hotel employees noticed that post was acting suspiciously on the morning of the accident ",
            "confidence": 0.91
          }
        ]
      },
      {
        "final": true,
        "alternatives": [
          {
            "transcript": "before leaving the hotel for his morning run and post made sure that the concierge knew who he was thanking her for a favor she did for him the day before I believe you're the one that tells about the tentacle gardens mom wife finally had a chance to visit there yesterday spectacular really wonderful I'm so glad and the hotel doorman said the post introduced himself by name before going out to restaurants ",
            "confidence": 0.81
          }
        ]
      },
      {
        "final": true,
        "alternatives": [
          {
            "transcript": "yes I am thank you my name is a post on a run this morning I'll be gone in about thirty minutes watch out for a nice run he made it a point to say good morning to the the woman at the hotel say who he was and what room he was in and that he was going to go out and job I mean like it was from the book of who cares at the dorm I didn't care ",
            "confidence": 0.8
          }
        ]
      },
      {
        "final": true,
        "alternatives": [
          {
            "transcript": "why would you do that ",
            "confidence": 0.96
          }
        ]
      },
      {
        "final": true,
        "alternatives": [
          {
            "transcript": "but all of these incidents simply raise suspicions homicide investigators had no hard evidence that and post played any role in his wife's death ",
            "confidence": 0.91
          }
        ]
      },
      {
        "final": true,
        "alternatives": [
          {
            "transcript": "investigators decided to conduct more sophisticated tests on the broken ",
            "confidence": 0.89
          }
        ]
      },
      {
        "final": true,
        "alternatives": [
          {
            "transcript": "to see if a woman Julie post size could have pulled it from the wall during the fourth ",
            "confidence": 0.74
          }
        ]
      },
      {
        "final": true,
        "alternatives": [
          {
            "transcript": "prosecutors in St Louis we're starting to wonder whether the death of Julie post in the hotel back ",
            "confidence": 0.85
          }
        ]
      },
      {
        "final": true,
        "alternatives": [
          {
            "transcript": "was truly an accident ",
            "confidence": 0.88
          }
        ]
      },
      {
        "final": true,
        "alternatives": [
          {
            "transcript": "the autopsy did not find any evidence of foul play so prosecutors decided to aids you delete posts remains for a second autopsy ",
            "confidence": 0.89
          }
        ]
      },
      {
        "final": true,
        "alternatives": [
          {
            "transcript": "she had been buried in the cemetery outside of New Orleans the water table is so high in New Orleans but most people are buried in above ground faults but Julie post had been buried in the ground and her body was placed in a wooden casket investigators feared that water damage to the body would be significant when they opened the grave it was almost completely filled with water fortunately the foot of the casket was the part that sunk her head was the only part of a body that was not submerged in water in our head ",
            "confidence": 0.88
          }
        ]
      },
      {
        "final": true,
        "alternatives": [
          {
            "transcript": "was in perfect shape the casket had collapsed and push down added pressed flattened her nose from the pressure but that was the only just figuration from the collapsing of the casket most of the casket collapse had been at the foot down the path ology is to perform the second autopsy found numerous bruises that were not noted during the first autopsy that's not unusual because some bruising continues to develop even after death add posts attorney said that the additional Bruce's proven nothing that they could have been caused by the removing of her organs and bones for donation shortly after her death ",
            "confidence": 0.83
          }
        ]
      },
      {
        "final": true,
        "alternatives": [
          {
            "transcript": "but the path all they just found two new Bruce is in a critical area the only additional findings at the autopsy ",
            "confidence": 0.81
          }
        ]
      },
      {
        "final": true,
        "alternatives": [
          {
            "transcript": "was an area bruising that was very low that far down the back of the head in the upper neck region %HESITATION wear it in a normal on top so usually don't take the scalp down quite that far but I'm looking at these bruises and as far as I'm concerned it's from a song and a hand ",
            "confidence": 0.79
          }
        ]
      },
      {
        "final": true,
        "alternatives": [
          {
            "transcript": "you're holding somebody under water ",
            "confidence": 0.74
          }
        ]
      },
      {
        "final": true,
        "alternatives": [
          {
            "transcript": "I got a hold of my face and neck ",
            "confidence": 0.47
          }
        ]
      },
      {
        "final": true,
        "alternatives": [
          {
            "transcript": "next prosecutors turned their attention to the metal Howell Raines found inside the top next to Julie posts body ",
            "confidence": 0.81
          }
        ]
      },
      {
        "final": true,
        "alternatives": [
          {
            "transcript": "the total ring was attached to metal stocks inside the wall one and a half ",
            "confidence": 0.68
          }
        ]
      },
      {
        "final": true,
        "alternatives": [
          {
            "transcript": "the ring and wall mounted been designed and manufactured to withstand hundreds of pounds of force ",
            "confidence": 0.92
          }
        ]
      },
      {
        "final": true,
        "alternatives": [
          {
            "transcript": "prosecutors hired boulder Kelsey and accident reconstruction is to attempt to recreate the accident ",
            "confidence": 0.86
          }
        ]
      },
      {
        "final": true,
        "alternatives": [
          {
            "transcript": "Kelsey conducted his experiments at the hotel on ",
            "confidence": 0.94
          }
        ]
      },
      {
        "final": true,
        "alternatives": [
          {
            "transcript": "in a room with an identical powering attached to the wall in the same way as the towel ring in and then Julie posed a room and for the test Kelsey used a woman who was the same height and weight as Julie post Kelsey asked the model to simulate a fall by grabbing on to the towel ring with all of her way ",
            "confidence": 0.77
          }
        ]
      },
      {
        "final": true,
        "alternatives": [
          {
            "transcript": "nothing happened ",
            "confidence": 0.75
          }
        ]
      },
      {
        "final": true,
        "alternatives": [
          {
            "transcript": "then she was asked to wrench the ring back and forth again nothing happened ",
            "confidence": 0.75
          }
        ]
      },
      {
        "final": true,
        "alternatives": [
          {
            "transcript": "what we found was that %HESITATION doing some calculations are based on what information we had on the ultimate strength of the ring that we could not remove it by a person can remove it at that site unless she fell about sixty four feet and grabbed the towering as she went by and of course the hotel room is an eight foot ceiling so there's no way that that could happen ",
            "confidence": 0.87
          }
        ]
      },
      {
        "final": true,
        "alternatives": [
          {
            "transcript": "finally as a last resort Kelsey asked the model to use both hands to remove the towel ring in any way she caught ",
            "confidence": 0.83
          }
        ]
      },
      {
        "final": true,
        "alternatives": [
          {
            "transcript": "after considerable effort the rain came off ",
            "confidence": 0.84
          }
        ]
      },
      {
        "final": true,
        "alternatives": [
          {
            "transcript": "concept the Julie post somehow ram this towering during the fall ",
            "confidence": 0.74
          }
        ]
      },
      {
        "final": true,
        "alternatives": [
          {
            "transcript": "and pulled it off the wall was impossible it could not physically have happened that way ",
            "confidence": 0.92
          }
        ]
      },
      {
        "final": true,
        "alternatives": [
          {
            "transcript": "next prosecutors sent an identical powering and wall mount the doctor William winds a professor of mechanical engineering at the university of Nebraska in Lincoln ",
            "confidence": 0.82
          }
        ]
      },
      {
        "final": true,
        "alternatives": [
          {
            "transcript": "Dr wines was asked to determine how much force was required to remove the towel ring from the wall attachment those test revealed that it took between four hundred eighty and five hundred pounds of force to remove it from the wall ",
            "confidence": 0.88
          }
        ]
      },
      {
        "final": true,
        "alternatives": [
          {
            "transcript": "it was also obvious very early on the testing that those types of moments of %HESITATION force application straight polls poles down clearly didn't match the evidence that the deformed hollering the fail tolerate didn't look anything like the tolerant in question here the base plate had damage underneath the spam and on the left side the towel ring itself also had been damaged ",
            "confidence": 0.78
          }
        ]
      },
      {
        "final": true,
        "alternatives": [
          {
            "transcript": "Dr winds perform twenty three different tests to reproduce the damage found on the base plate and powering all without success ",
            "confidence": 0.84
          }
        ]
      },
      {
        "final": true,
        "alternatives": [
          {
            "transcript": "but on the test number twenty four Dr wines produced something very close that test indicated that the towel ring was removed from outside the back top ",
            "confidence": 0.73
          }
        ]
      },
      {
        "final": true,
        "alternatives": [
          {
            "transcript": "our conclusion was that it was taken off the wall by someone with considerable strength and it was %HESITATION you know the type of action where one would grab it and pull outside the tub and it was %HESITATION ",
            "confidence": 0.92
          }
        ]
      },
      {
        "final": true,
        "alternatives": [
          {
            "transcript": "%HESITATION in the if you look at the location of it it would be consistent for instance was someone like putting your foot on the edge of the tub and grabbing a towering and then pulling it off out out toward the outside of the tub prosecutors now had scientific proof that you only post death was no accident ",
            "confidence": 0.86
          }
        ]
      },
      {
        "final": true,
        "alternatives": [
          {
            "transcript": "in nineteen eighty six New Orleans was going through its worst economic downturn since the Great Depression many local businesses were affected and real estate was just one more casualty ",
            "confidence": 0.96
          }
        ]
      },
      {
        "final": true,
        "alternatives": [
          {
            "transcript": "and post was ten percent owner of the Wagner Truax real estate business and was responsible for ten percent of the losses which in nineteen eighty five and eighty six were substantial and the post's marriage was going through a down turn of its own friend said that individually for frequently fights which were sometimes physical and chemical tanks who worked with the post said posted made advances towards her in the months before Julie's back ",
            "confidence": 0.78
          }
        ]
      },
      {
        "final": true,
        "alternatives": [
          {
            "transcript": "I think that had fell in love with kimo tan just him being a free man ",
            "confidence": 0.62
          }
        ]
      },
      {
        "final": true,
        "alternatives": [
          {
            "transcript": "I wouldn't get killed ",
            "confidence": 0.59
          }
        ]
      },
      {
        "final": true,
        "alternatives": [
          {
            "transcript": "he had to be a free man with lots of money ",
            "confidence": 0.81
          }
        ]
      },
      {
        "final": true,
        "alternatives": [
          {
            "transcript": "to compete with her husband ",
            "confidence": 0.96
          }
        ]
      },
      {
        "final": true,
        "alternatives": [
          {
            "transcript": "and he hatched this plan ",
            "confidence": 0.64
          }
        ]
      },
      {
        "final": true,
        "alternatives": [
          {
            "transcript": "prosecutors believe that plan was in motion one month before Julie's death when ed post increased his wife's life insurance ",
            "confidence": 0.89
          }
        ]
      },
      {
        "final": true,
        "alternatives": [
          {
            "transcript": "on June third nineteen eighty six before going out for his morning run prosecutors believe that close drowned his wife in the hotel bath top ",
            "confidence": 0.85
          }
        ]
      },
      {
        "final": true,
        "alternatives": [
          {
            "transcript": "after which ",
            "confidence": 0.99
          }
        ]
      },
      {
        "final": true,
        "alternatives": [
          {
            "transcript": "the towel ring from the wall not only to corroborate his cover story the Julie fell while holding on to the towering but also for the money the potential settlement from the hotel in a civil lawsuit ",
            "confidence": 0.78
          }
        ]
      },
      {
        "final": true,
        "alternatives": [
          {
            "transcript": "after the market post made sure to speak with both the hotel concierge and doorman to cementing his alibi thank you my name is ed ",
            "confidence": 0.82
          }
        ]
      },
      {
        "final": true,
        "alternatives": [
          {
            "transcript": "I run this ",
            "confidence": 0.6
          }
        ]
      },
      {
        "final": true,
        "alternatives": [
          {
            "transcript": "the whole business with the towering which is really what killed him not literally but figuratively ",
            "confidence": 0.89
          }
        ]
      },
      {
        "final": true,
        "alternatives": [
          {
            "transcript": "you know he had to go pull that off the wall ",
            "confidence": 0.99
          }
        ]
      },
      {
        "final": true,
        "alternatives": [
          {
            "transcript": "he had to go pull that off the wall so that he could set up a lawsuit against the omni hotel and get more money ",
            "confidence": 0.94
          }
        ]
      },
      {
        "final": true,
        "alternatives": [
          {
            "transcript": "the greedy SOB ",
            "confidence": 0.91
          }
        ]
      },
      {
        "final": true,
        "alternatives": [
          {
            "transcript": "three years after Julie post death and post went on trial for first degree murder ",
            "confidence": 0.82
          }
        ]
      },
      {
        "final": true,
        "alternatives": [
          {
            "transcript": "a post pleaded not guilty and took the stand in his own defense it's demeanor on the stand I think could best be described ",
            "confidence": 0.89
          }
        ]
      },
      {
        "final": true,
        "alternatives": [
          {
            "transcript": "as follows ",
            "confidence": 0.94
          }
        ]
      },
      {
        "final": true,
        "alternatives": [
          {
            "transcript": "he was very well dressed he was very articulate spoke at a very a sophisticated level %HESITATION including his use of the language %HESITATION spoke I think of far differently than the jurors were accustomed to speaking or hearing %HESITATION he did not speak with a southern accent at all although he was from New Orleans %HESITATION ",
            "confidence": 0.93
          }
        ]
      },
      {
        "final": true,
        "alternatives": [
          {
            "transcript": "and he came across as it as it often came across as condescending ",
            "confidence": 0.89
          }
        ]
      },
      {
        "final": true,
        "alternatives": [
          {
            "transcript": "and I think that %HESITATION those things did not play well in the scientific experts provided powerful testimony that Julie post was not capable of removing the powering during the fall ",
            "confidence": 0.88
          }
        ]
      },
      {
        "final": true,
        "alternatives": [
          {
            "transcript": "it took the jury less than a day to reach its verdict ",
            "confidence": 0.81
          }
        ]
      },
      {
        "final": true,
        "alternatives": [
          {
            "transcript": "a post was found guilty of first degree murder and was sentenced to life in prison without the possibility of parole ",
            "confidence": 0.97
          }
        ]
      },
      {
        "final": true,
        "alternatives": [
          {
            "transcript": "add post and his attorneys appealed the conviction and in a plea bargain posted breed to plead guilty to second degree murder and confessed to the murder of his wife in exchange for a thirty year prison sentence that included the possibility of parole if he doesn't take ",
            "confidence": 0.91
          }
        ]
      },
      {
        "final": true,
        "alternatives": [
          {
            "transcript": "he gets away with ",
            "confidence": 0.64
          }
        ]
      },
      {
        "final": true,
        "alternatives": [
          {
            "transcript": "just an accidental drowning ",
            "confidence": 0.69
          }
        ]
      },
      {
        "final": true,
        "alternatives": [
          {
            "transcript": "what happened almost everybody classified it as undetermined or accident ",
            "confidence": 0.74
          }
        ]
      },
      {
        "final": true,
        "alternatives": [
          {
            "transcript": "but for that ",
            "confidence": 0.76
          }
        ]
      },
      {
        "final": true,
        "alternatives": [
          {
            "transcript": "post to be honest merry way probably should be on it a couple million dollars ",
            "confidence": 0.55
          }
        ]
      },
      {
        "final": true,
        "alternatives": [
          {
            "transcript": "at seven thousand nine ",
            "confidence": 0.75
          }
        ]
      },
      {
        "final": true,
        "alternatives": [
          {
            "transcript": "in my opinion ",
            "confidence": 0.99
          }
        ]
      },
      {
        "final": true,
        "alternatives": [
          {
            "transcript": "the most important thing ",
            "confidence": 0.91
          }
        ]
      },
      {
        "final": true,
        "alternatives": [
          {
            "transcript": "%HESITATION in the trial ",
            "confidence": 0.72
          }
        ]
      },
      {
        "final": true,
        "alternatives": [
          {
            "transcript": "was the sign was the towel ring ",
            "confidence": 0.58
          }
        ]
      },
      {
        "final": true,
        "alternatives": [
          {
            "transcript": "you can show that it was rich back and forth back and forth until it came loose %HESITATION ",
            "confidence": 0.94
          }
        ]
      },
      {
        "final": true,
        "alternatives": [
          {
            "transcript": "that can take today if he ever left that out of there ",
            "confidence": 0.5
          }
        ]
      },
      {
        "final": true,
        "alternatives": [
          {
            "transcript": "the free ",
            "confidence": 0.49
          }
        ]
      },
      {
        "final": true,
        "alternatives": [
          {
            "transcript": "for ",
            "confidence": 0.65
          }
        ]
      }
    ],
    "result_index": 0
  }
]